klarenz/__init__.py
klarenz/cfg.py
klarenz/classes.py
klarenz/const.py
klarenz/copyr.py
klarenz/ly.py
klarenz/main.py
klarenz/misc.py
klarenz/pitch.py
klarenz/process.py
klarenz/rhythm.py
klarenz/version.py
klarenz-190624.dist-info/LICENSE
klarenz-190624.dist-info/METADATA
klarenz-190624.dist-info/WHEEL
klarenz-190624.dist-info/top_level.txt
klarenz-190624.dist-info/RECORD
