Metadata-Version: 2.1
Name: klarenz
Version: 190624
Summary: Programmatically generate Lilypond scores, with ease and elegance of pure Python
Home-page: https://github.com/teymuri/klarenz.git
Author: Amir Teymuri
Author-email: Amir Teymuri <amtework@gmail.com>
Project-URL: Homepage, https://klarenz.codeberg.page/
Project-URL: Bug Tracker, https://codeberg.org/klarenz/klarenz/issues
Classifier: Programming Language :: Python :: 3
Classifier: License :: OSI Approved :: GNU Affero General Public License v3
Classifier: Operating System :: OS Independent
Requires-Python: >=3.5
License-File: LICENSE
Requires-Dist: pytest
